{
  "$schema": "https://developer.microsoft.com/json-schemas/fabric/item/report/definition/visualContainer/2.9.0/schema.json",
  "name": "linenetsurplus00000a07",
  "position": {
    "x": 20,
    "y": 180,
    "z": 6,
    "height": 260,
    "width": 780
  },
  "visual": {
    "visualType": "lineChart",
    "query": {
      "queryState": {
        "Category": {
          "projections": [
            {
              "field": {
                "Column": {
                  "Expression": {
                    "SourceRef": {
                      "Entity": "DimDate"
                    }
                  },
                  "Property": "Month & Year"
                }
              },
              "queryRef": "DimDate.Month & Year",
              "nativeQueryRef": "Month & Year",
              "active": true
            }
          ]
        },
        "Y": {
          "projections": [
            {
              "field": {
                "Measure": {
                  "Expression": {
                    "SourceRef": {
                      "Entity": "Measure Table"
                    }
                  },
                  "Property": "Total Income"
                }
              },
              "queryRef": "Measure Table.Total Income",
              "nativeQueryRef": "Total Income"
            },
            {
              "field": {
                "Measure": {
                  "Expression": {
                    "SourceRef": {
                      "Entity": "Measure Table"
                    }
                  },
                  "Property": "Total Expenses"
                }
              },
              "queryRef": "Measure Table.Total Expenses",
              "nativeQueryRef": "Total Expenses"
            },
            {
              "field": {
                "Measure": {
                  "Expression": {
                    "SourceRef": {
                      "Entity": "Measure Table"
                    }
                  },
                  "Property": "Net Surplus"
                }
              },
              "queryRef": "Measure Table.Net Surplus",
              "nativeQueryRef": "Net Surplus"
            }
          ]
        }
      },
      "sortDefinition": {
        "sort": [
          {
            "field": {
              "Column": {
                "Expression": {
                  "SourceRef": {
                    "Entity": "DimDate"
                  }
                },
                "Property": "Month & Year"
              }
            },
            "direction": "Ascending"
          }
        ],
        "isDefaultSort": true
      }
    },
    "drillFilterOtherVisuals": true
  }
}