{
  "$schema": "https://developer.microsoft.com/json-schemas/fabric/item/report/definition/visualContainer/2.9.0/schema.json",
  "name": "cashline000a000c",
  "position": {
    "x": 30,
    "y": 820,
    "z": 11,
    "height": 242,
    "width": 1860
  },
  "visual": {
    "visualType": "lineChart",
    "query": {
      "queryState": {
        "Category": {
          "projections": [
            {
              "field": {
                "Column": {
                  "Expression": {
                    "SourceRef": {
                      "Entity": "DimDate"
                    }
                  },
                  "Property": "Month & Year"
                }
              },
              "queryRef": "DimDate.Month & Year",
              "nativeQueryRef": "Month & Year",
              "active": true
            }
          ]
        },
        "Y": {
          "projections": [
            {
              "field": {
                "Measure": {
                  "Expression": {
                    "SourceRef": {
                      "Entity": "Measure Table"
                    }
                  },
                  "Property": "Cumulative Cash Position"
                }
              },
              "queryRef": "Measure Table.Cumulative Cash Position",
              "nativeQueryRef": "Cumulative Cash Position"
            }
          ]
        }
      },
      "sortDefinition": {
        "sort": [
          {
            "field": {
              "Column": {
                "Expression": {
                  "SourceRef": {
                    "Entity": "DimDate"
                  }
                },
                "Property": "Month & Year"
              }
            },
            "direction": "Ascending"
          }
        ],
        "isDefaultSort": true
      }
    },
    "objects": {
      "labels": [
        {
          "properties": {
            "show": {
              "expr": {
                "Literal": {
                  "Value": "false"
                }
              }
            }
          }
        }
      ],
      "y1AxisReferenceLine": [
        {
          "properties": {
            "show": {
              "expr": {
                "Literal": {
                  "Value": "true"
                }
              }
            },
            "value": {
              "expr": {
                "Literal": {
                  "Value": "0D"
                }
              }
            },
            "displayName": {
              "expr": {
                "Literal": {
                  "Value": "'Break-even'"
                }
              }
            },
            "lineColor": {
              "solid": {
                "color": {
                  "expr": {
                    "Literal": {
                      "Value": "'#C62F2F'"
                    }
                  }
                }
              }
            },
            "transparency": {
              "expr": {
                "Literal": {
                  "Value": "0D"
                }
              }
            },
            "style": {
              "expr": {
                "Literal": {
                  "Value": "'dashed'"
                }
              }
            }
          }
        }
      ]
    },
    "drillFilterOtherVisuals": true
  }
}